okab/__init__.py
okab/__main__.py
okab/_version.py
okab/bin/okab
okab/bin/fonts/liberation-fonts-ttf-2.1.5/AUTHORS
okab/bin/fonts/liberation-fonts-ttf-2.1.5/ChangeLog
okab/bin/fonts/liberation-fonts-ttf-2.1.5/LICENSE
okab/bin/fonts/liberation-fonts-ttf-2.1.5/LiberationMono-Bold.ttf
okab/bin/fonts/liberation-fonts-ttf-2.1.5/LiberationMono-BoldItalic.ttf
okab/bin/fonts/liberation-fonts-ttf-2.1.5/LiberationMono-Italic.ttf
okab/bin/fonts/liberation-fonts-ttf-2.1.5/LiberationMono-Regular.ttf
okab/bin/fonts/liberation-fonts-ttf-2.1.5/LiberationSans-Bold.ttf
okab/bin/fonts/liberation-fonts-ttf-2.1.5/LiberationSans-BoldItalic.ttf
okab/bin/fonts/liberation-fonts-ttf-2.1.5/LiberationSans-Italic.ttf
okab/bin/fonts/liberation-fonts-ttf-2.1.5/LiberationSans-Regular.ttf
okab/bin/fonts/liberation-fonts-ttf-2.1.5/LiberationSerif-Bold.ttf
okab/bin/fonts/liberation-fonts-ttf-2.1.5/LiberationSerif-BoldItalic.ttf
okab/bin/fonts/liberation-fonts-ttf-2.1.5/LiberationSerif-Italic.ttf
okab/bin/fonts/liberation-fonts-ttf-2.1.5/LiberationSerif-Regular.ttf
okab/bin/fonts/liberation-fonts-ttf-2.1.5/README.md
okab/bin/fonts/liberation-fonts-ttf-2.1.5/TODO
okab/saver/__init__.py
okab/saver/_okab.py
okab-22.8a1.dist-info/LICENSE
okab-22.8a1.dist-info/METADATA
okab-22.8a1.dist-info/WHEEL
okab-22.8a1.dist-info/entry_points.txt
okab-22.8a1.dist-info/top_level.txt
okab-22.8a1.dist-info/RECORD
