Metadata-Version: 2.1
Name: okab
Version: 22.8a1
Summary: altair + okab = static beauty
Author-email: Daylin Morgan <daylinmorgan@gmail.com>
License: MIT
Requires-Python: >=3.7
License-File: LICENSE
Requires-Dist: importlib-resources (>=5.9.0) ; python_version < "3.9"
Provides-Extra: dev
Requires-Dist: black (>=22.6.0) ; extra == 'dev'
Requires-Dist: flake8 (>=5.0.4) ; extra == 'dev'
Requires-Dist: mypy (>=0.971) ; extra == 'dev'
Requires-Dist: altair (>=4.2.0) ; extra == 'dev'
Requires-Dist: altair-saver (>=0.5.0) ; extra == 'dev'
Requires-Dist: build (>=0.8.0) ; extra == 'dev'
Requires-Dist: vega-datasets (>=0.9.0) ; extra == 'dev'
Requires-Dist: setuptools (>=65.3.0) ; extra == 'dev'
Requires-Dist: setuptools-scm (>=7.0.5) ; extra == 'dev'
Requires-Dist: wheel (>=0.37.1) ; extra == 'dev'
